tallipoika/__init__.py
tallipoika/__main__.py
tallipoika/_factory.py
tallipoika/api.py
tallipoika/cli.py
tallipoika/py2es6.py
tallipoika/speedup.py
tallipoika-2024.1.7.dist-info/LICENSE
tallipoika-2024.1.7.dist-info/METADATA
tallipoika-2024.1.7.dist-info/WHEEL
tallipoika-2024.1.7.dist-info/entry_points.txt
tallipoika-2024.1.7.dist-info/top_level.txt
tallipoika-2024.1.7.dist-info/RECORD
